build/lib/dbt/adapters/splitgraph/__init__.py
build/lib/dbt/adapters/splitgraph/connections.py
build/lib/dbt/adapters/splitgraph/impl.py
build/lib/dbt/include/splitgraph/__init__.py
dbt/adapters/splitgraph/__init__.py
dbt/adapters/splitgraph/connections.py
dbt/adapters/splitgraph/impl.py
dbt/include/splitgraph/__init__.py
dbt/include/splitgraph/dbt_project.yml
dbt/include/splitgraph/macros/adapters.sql
dbt/include/splitgraph/macros/catalog.sql
dbt/include/splitgraph/macros/relations.sql
dbt_splitgraph-0.0.1.dist-info/METADATA
dbt_splitgraph-0.0.1.dist-info/WHEEL
dbt_splitgraph-0.0.1.dist-info/top_level.txt
dbt_splitgraph-0.0.1.dist-info/RECORD
